pyrocopy
