Metadata-Version: 1.1
Name: pyrocopy
Version: 0.8.0
Summary: A suite of robust file copying utilities for Python.
Home-page: https://github.com/caskater4/pyrocopy
Author: Jean-Philippe Steinmetz
Author-email: caskater47@gmail.com
License: MIT
Keywords: file utilities admin filesystem copy move mirror sync
Platform: UNKNOWN
Classifier: Development Status :: 4 - Beta
Classifier: Intended Audience :: Developers
Classifier: Intended Audience :: End Users/Desktop
Classifier: Topic :: Software Development :: Libraries
Classifier: Topic :: System :: Systems Administration
Classifier: Topic :: Utilities
Classifier: License :: OSI Approved :: MIT License
Classifier: Programming Language :: Python :: 2.7
